slackest/__init__.py
slackest/api.py
slackest/apps.py
slackest/apps_permissions.py
slackest/auth.py
slackest/base_api.py
slackest/bots.py
slackest/channels.py
slackest/chat.py
slackest/constants.py
slackest/conversation.py
slackest/dialog.py
slackest/dnd.py
slackest/emoji.py
slackest/files.py
slackest/files_comments.py
slackest/groups.py
slackest/idp_groups.py
slackest/im.py
slackest/incoming_webhook.py
slackest/mpim.py
slackest/oauth.py
slackest/pins.py
slackest/presence.py
slackest/reactions.py
slackest/reminders.py
slackest/response.py
slackest/rtm.py
slackest/search.py
slackest/slackest.py
slackest/slackest_error.py
slackest/stars.py
slackest/team.py
slackest/team_profile.py
slackest/user_group_users.py
slackest/user_groups.py
slackest/users.py
slackest/users_admin.py
slackest/users_profile.py
slackest/utils.py
slackest-0.15.0.dist-info/LICENSE
slackest-0.15.0.dist-info/METADATA
slackest-0.15.0.dist-info/WHEEL
slackest-0.15.0.dist-info/top_level.txt
slackest-0.15.0.dist-info/RECORD
