Metadata-Version: 2.1
Name: slackest
Version: 0.15.0
Summary: Slack API client
Home-page: http://github.com/Cox-Automotive/slackest/
Author: Cox Automotive Cloud Team
Author-email: andrew.sledge@coxautoinc.com
License: http://www.apache.org/licenses/LICENSE-2.0
Keywords: slack api
Platform: UNKNOWN
Classifier: Intended Audience :: Developers
Classifier: License :: OSI Approved :: Apache Software License
Classifier: Natural Language :: English
Classifier: Programming Language :: Python
Classifier: Programming Language :: Python :: 3.7
Requires-Dist: requests (>=2.2.1)
